odoo8_addon_shopinvader_algolia-8.0.0.0.1.99.dev16-py3.8-nspkg.pth
odoo_addons/shopinvader_algolia/README.rst
odoo_addons/shopinvader_algolia/__init__.py
odoo_addons/shopinvader_algolia/__openerp__.py
odoo_addons/shopinvader_algolia/hooks.py
odoo_addons/shopinvader_algolia/data/ir_export_product.xml
odoo_addons/shopinvader_algolia/demo/backend_demo.xml
odoo_addons/shopinvader_algolia/demo/product_demo.xml
odoo_addons/shopinvader_algolia/models/.product_category.py.swo
odoo_addons/shopinvader_algolia/models/__init__.py
odoo_addons/shopinvader_algolia/models/product_category.py
odoo_addons/shopinvader_algolia/tests/__init__.py
odoo_addons/shopinvader_algolia/tests/test_export.py
odoo_addons/shopinvader_algolia/unit/__init__.py
odoo_addons/shopinvader_algolia/unit/exporter.py
odoo8_addon_shopinvader_algolia-8.0.0.0.1.99.dev16.dist-info/METADATA
odoo8_addon_shopinvader_algolia-8.0.0.0.1.99.dev16.dist-info/WHEEL
odoo8_addon_shopinvader_algolia-8.0.0.0.1.99.dev16.dist-info/namespace_packages.txt
odoo8_addon_shopinvader_algolia-8.0.0.0.1.99.dev16.dist-info/top_level.txt
odoo8_addon_shopinvader_algolia-8.0.0.0.1.99.dev16.dist-info/RECORD
